Workbook

Sheet Radar
A1: ID_CASO | B1: ORGANISMO | C1: TIPO_NORMA | D1: NUMERO_NORMA | E1: PALABRAS_CLAVE | F1: ACCION_ESPERADA | G1: ESTADO
A2: DESREG-001 | B2: PEN | C2: Resolución | D2: 322/2023 | E2: CERTIFICADO UNICO DE DISCAPACIDAD, DISCAPACIDAD, ACTUALIZACION CUD | F2: Modificación | G2: Inactivo
A3: DESREG-002 | B3: PEN | C3: Decreto | D3: 1187/2012 | E3: CAJA DE AHORRO, BANCO DE LA NACION ARGENTINA, HABERES | F3: Modificación | G3: Inactivo
A4: DESREG-003 | B4: PEN | C4: Decreto | D4: 1191/2012 | E4: AEROLINEAS ARGENTINAS, PASAJES AEREOS, AUSTRAL | F4: Modificación | G4: Inactivo
A5: DESREG-004 | B5: PEN | C5: Decreto | D5: 557/2023 | E5: ARANCEL EXTERNO COMUN, MERCOSUR | F5: Modificación | G5: Inactivo
A6: DESREG-005 | B6: PEN | C6: Decreto | D6: 557/2023 | E6: BIENES DE INFORMATICA Y TELECOMUNICACIONES, ARANCELES DE IMPORTACION | F6: Modificación | G6: Inactivo
A7: DESREG-006 | B7: PEN | C7: Disposición | D7: 21/2023 | E7: TRASBORDO BUQUE A BUQUE, SHIP TO SHIP, TRASBORDO | F7: Modificación | G7: Inactivo
A8: DESREG-007 | B8: PEN | C8: Decreto | D8: 256/2010 | E8: ISLAS MALVINAS, PUERTOS CONTINENTALES, TRANSITO MARITIMO | F8: Modificación | G8: Pendiente
A9: DESREG-008 | B9: PLN | C9: Ley | D9: 27419 | E9: MARINA MERCANTE, ANTIGUEDAD MAXIMA, BUQUES | F9: Derogación | G9: Pendiente
A10: DESREG-009 | B10: PLN | C10: Ley | D10: 19492 | E10: TRIPULACION MINIMA, MARINA MERCANTE, GREMIOS | F10: Modificación | G10: Inactivo
A11: DESREG-010 | B11: PLN | C11: Ley | D11: 27418 | E11: PREFECTURA NAVAL, TALLERES NAVALES, BUQUES, REPARACION | F11: Modificación | G11: Pendiente
A12: DESREG-011 | B12: PEN | C12: Decreto | D12: 2694/1991 | E12: PILOTAJE, PRACTICOS, MANIOBRA SHIP TO SHIP | F12: Modificación | G12: Pendiente
A13: DESREG-012 | B13: PLN | C13: Ley | D13: 14250 | E13: ULTRAACTIVIDAD, CONVENIOS COLECTIVOS | F13: Modificación | G13: Inactivo
A14: DESREG-013 | B14: PLN | C14: Ley | D14: 14250 | E14: CONVENCIONES COLECTIVAS, DESCENTRALIZACION, NEGOCIACION COLECTIVA | F14: Modificación | G14: Inactivo
A15: DESREG-014 | B15: PLN | C15: Ley | D15: 14250 | E15: ARBITRAJE, CONFLICTOS LABORALES, CONVENIOS DE TRABAJO | F15: Modificación | G15: Pendiente
A16: DESREG-015 | B16: PLN | C16: Ley | D16: 12.988/1947 | E16: SEGUROS EN EL EXTERIOR, ASEGURADORAS, ASEGURAR RIESGOS | F16: Modificación | G16: Pendiente
A17: DESREG-016 | B17: PEN | C17: Decreto | D17: 2426/2012 | E17: ASIGNACION DE FRECUENCIAS, FRECUENCIAS, ESPECTRO RADIOELECTRICO | F17: Modificación | G17: Pendiente
A18: DESREG-017 | B18: PEN | C18: Decreto | D18: 915/2010 | E18: PARQUES INDUSTRIALES, REGISTRO NACIONAL DE PARQUES INDUSTRIALES, RENPI | F18: Modificación | G18: Inactivo
A19: DESREG-018 | B19: PEN | C19: Decreto | D19: 68/2022 | E19: APORTES NO REINTEGRABLES, PARQUES INDUSTRIALES, RENPI | F19: Modificación | G19: Inactivo
A20: DESREG-019 | B20: PEN | C20: Resolución | D20: 155/2007 | E20: PRODUCTORES DE PAPA, MINORISTAS, COMPENSACION | F20: Modificación | G20: Inactivo
A21: DESREG-020 | B21: PEN | C21: Resolución | D21: 684/2014 | E21: PRODUCTORES TAMBEROS, TAMBEROS, PRODUCCION LECHERA | F21: Modificación | G21: Inactivo
A22: DESREG-021 | B22: PEN | C22: Resolución | D22: 208/2014 | E22: PRODUCTORES TAMBEROS, REGISTRO DE BENEFICIARIOS, TAMBEROS | F22: Modificación | G22: Inactivo
A23: DESREG-022 | B23: PEN | C23: Resolución | D23: 50/2015 | E23: PATROCINIO JURIDICO GRATUITO, CONFLICTOS DE CONSUMO | F23: Modificación | G23: Inactivo
A24: DESREG-023 | B24: PEN | C24: Resolución | D24: 38718 | E24: PRECIOS MAXIMOS, CADENA DE LA CARNE, CARNE | F24: Derogación | G24: Inactivo
A25: DESREG-024 | B25: PEN | C25: Resolución | D25: 42370 | E25: EL MERCADO EN TU BARRIO, FERIAS AGROALIMENTARIAS | F25: Modificación | G25: Inactivo
A26: DESREG-025 | B26: ENACOM | C26: Resolución | D26: 3597/2016 | E26: PROGRAMA CONECTIVIDAD, AREAS RURALES, TELECOMUNICACIONES | F26: Modificación | G26: Inactivo
A27: DESREG-026 | B27: Secretaría de Comercio | C27: Resolución | D27: 63/2011 | E27: MERCADOS CONCENTRADORES | F27: Modificación | G27: Inactivo
A28: DESREG-027 | B28: Secretaría de Agricultura | C28: Resolución | D28: 1280/2023 | E28: APORTE DE NUTRIENTES, FERTILIZACION NITROGENADA, TRIGO Y MAIZ | F28: Modificación | G28: Inactivo
A29: DESREG-028 | B29: Secretaría de Alimentos, Bioeconomia y Desarrollo Regional | C29: Resolución | D29: 142/2021 | E29: AGROPYMES SUSTENTABLES, BIOECONOMIA | F29: Modificación | G29: Inactivo
A30: DESREG-029 | B30: Secretaría de Calidad en Salud y Secretaría de Alimentos, Bioeconomia y Desarrollo Regional | C30: Resolución | D30: 26/2021 | E30: REGISTRO NACIONAL DE PRODUCTO ALIMENTICIO, CODIGO ALIMENTARIO ARGENTINO, ROTULO | F30: Modificación | G30: Pendiente
A31: DESREG-030 | B31: Ministerio de Desarrollo Productivo | C31: Resolución | D31: 26/2021 | E31: CAPACITACION DE LAS PYMES, AGENCIA DE PROMOCION, PYMES | F31: Modificación | G31: Pendiente
A32: DESREG-031 | B32: Dirección Nacional de Control Agropecuario | C32: Disposición | D32: A9/2019 | E32: COMPRAVENTA DE GRANOS, TIPO DE CAMBIO, DOLAR DIVISA BNA | F32: Modificación | G32: Inactivo
A33: DESREG-032 | B33: ANMAT | C33: Disposición | D33: 1675/2014 | E33: SUPLEMENTOS DIETARIOS, REGISTRO NACIONAL DE ESTABLECIMIENTOS, PRODUCTOS ALIMENTICIOS | F33: Modificación | G33: Pendiente
A34: DESREG-033 | B34: CNV | C34: Resolución | D34: 1025/2024 | E34: PRESTADORES DE SERVICIOS CON ACTIVOS VIRTUALES, ACTIVOS VIRTUALES, CRYPTO | F34: Modificación | G34: Inactivo
A35: DESREG-034 | B35: PLN | C35: Ley | D35: 26854 | E35: MEDIDAS CAUTELARES, CONCESION DE MEDIDAS CAUTELARES | F35: Modificación | G35: Pendiente
A36: DESREG-035 | B36: PLN | C36: Ley | D36: 25344 | E36: EMERGENCIA ECONOMICA, DEMANDA CONTRA EL ESTADO, TRASLADO DE DEMANDA | F36: Modificación | G36: Pendiente
A37: DESREG-036 | B37: PLN | C37: Ley | D37: 25345 | E37: PAGOS EN EFECTIVO, MEDIOS DE PAGO, FACTURACION | F37: Modificación | G37: Pendiente
A38: DESREG-037 | B38: PLN | C38: Ley | D38: 19549 | E38: DOCUMENTO QUE EMITE EL ESTADO, REFORMA PINEIRA, CERTIFICADO DE ANTECEDENTES | F38: Modificación | G38: Pendiente
A39: DESREG-038 | B39: AFIP/ARCA | C39: Resolución | D39: Varios regímenes de información AFIP | E39: REGIMENES DE INFORMACION, REGIMEN DE INFORMACION | F39: Derogación | G39: Pendiente
A40: DESREG-039 | B40: PLN | C40: Ley | D40: 19550 | E40: SOCIEDADES EXTRANJERAS, SOCIEDAD LOCAL, INSCRIPCION REGISTRAL | F40: Modificación | G40: Pendiente
A41: DESREG-040 | B41: IGJ | C41: Resolución | D41: 42248 | E41: GARANTIA DE DIRECTORES, SEGURO DE CAUCION, IGJ | F41: Modificación | G41: Inactivo
A42: DESREG-041 | B42: ANMAT | C42: Disposición | D42: 3226/2011 | E42: CIGARRILLO ELECTRONICO, NICOTINA, VAPEO | F42: Modificación | G42: Inactivo
A43: DESREG-042 | B43: Ministerio de Salud | C43: Resolución | D43: 565/2023 | E43: PRODUCTOS DE TABACO CALENTADO, TABACO, DISPOSITIVOS ELECTRONICOS | F43: Modificación | G43: Inactivo
A44: DESREG-043 | B44: SENASA | C44: Resolución | D44: 1678/2019 | E44: REGISTRO NACIONAL FITOSANITARIO, VIVEROS, RENFO | F44: Modificación | G44: Inactivo
A45: DESREG-044 | B45: SENASA | C45: Resolución | D45: 1039/2018 | E45: RESPONSABLE TECNICO, REGISTRO NACIONAL UNICO DE RESPONSABLES TECNICOS, SENASA | F45: Modificación | G45: Pendiente
A46: DESREG-045 | B46: BCRA | C46: Comunicación "A" | D46: 7535 | E46: ENVIOS POSTALES, FINANCIACION EN CUOTAS, COMPRAS INTERNACIONALES | F46: Modificación | G46: Pendiente
A47: DESREG-046 | B47: PEN | C47: Resolución | D47: 5608/2024 | E47: DIRECCION FISCAL ELECTRONICA, REGIMEN DE PEQUENOS ENVIOS, TRAMITES ADUANEROS | F47: Modificación | G47: Inactivo
A48: DESREG-047 | B48: PEN | C48: Decreto | D48: 406/2019 | E48: BIENES USADOS, CIBU, IMPORTACION DE BIENES USADOS | F48: Modificación | G48: Inactivo
A49: DESREG-048 | B49: PEN | C49: Resolución | D49: 4447/2019 | E49: REGIMEN PUERTA A PUERTA, ENVIOS POSTALES | F49: Modificación | G49: Inactivo
A50: DESREG-049 | B50: PLN | C50: Ley | D50: 25467 | E50: PROMOCION DE LA CIENCIA, FINANCIAMIENTO DE LA CIENCIA, INVERSION PRIVADA | F50: Modificación | G50: Pendiente
A51: DESREG-050 | B51: PLN | C51: Ley | D51: Ley 19.459 | E51: SILENCIO ADMINISTRATIVO POSITIVO, AUTORIZACION ADMINISTRATIVA | F51: Modificación | G51: Inactivo
A52: DESREG-051 | B52: PLN | C52: Ley | D52: 19550 | E52: SOCIEDADES EXTRANJERAS, INSCRIPCION DE SOCIEDADES, IGJ | F52: Modificación | G52: Pendiente
A53: DESREG-052 | B53: IGJ | C53: Resolución | D53: 15/2024 | E53: FUNDACIONES, SIMPLIFICACION DE TRAMITES, REQUISITOS REDUNDANTES | F53: Modificación | G53: Pendiente
A54: DESREG-053 | B54: PLN | C54: Ley | D54: 27275 | E54: AGENCIA DE ACCESO A LA INFORMACION PUBLICA, ACCESO A LA INFORMACION | F54: Modificación | G54: Pendiente
A55: DESREG-054 | B55: PEN | C55: Decreto | D55: 157/2020 | E55: AGENCIA NACIONAL DE PROMOCION DE LA INVESTIGACION, DESARROLLO TECNOLOGICO E INNOVACION | F55: Modificación | G55: Pendiente
A56: DESREG-055 | B56: PLN | C56: Ley | D56: Ley 26.363 | E56: AGENCIA NACIONAL DE SEGURIDAD VIAL, SEGURIDAD VIAL | F56: Modificación | G56: Inactivo
A57: DESREG-056 | B57: PLN | C57: Ley | D57: Ley 27.669 | E57: AGENCIA REGULATORIA DEL CANAMO Y DEL CANNABIS MEDICINAL, ARICCAME, CANNABIS MEDICINAL | F57: Modificación | G57: Inactivo
A58: DESREG-057 | B58: PEN | C58: Decreto | D58: Decreto 1259/2003 | E58: ARCHIVO NACIONAL DE LA MEMORIA | F58: Modificación | G58: Inactivo
A59: DESREG-058 | B59: PLN | C59: Ley | D59: 23329 | E59: BALLET NACIONAL | F59: Modificación | G59: Pendiente
A60: DESREG-059 | B60: PLN | C60: Ley | D60: 26548 | E60: BANCO NACIONAL DE DATOS GENETICOS, DATOS GENETICOS | F60: Modificación | G60: Pendiente
A61: DESREG-060 | B61: PEN | C61: Decreto | D61: 195/2011 | E61: CASA PATRIA GRANDE, NESTOR CARLOS KIRCHNER | F61: Modificación | G61: Inactivo
A62: DESREG-061 | B62: PEN | C62: Decreto | D62: 348/2017 | E62: CENTRO CULTURAL DEL BICENTENARIO, NESTOR CARLOS KIRCHNER | F62: Modificación | G62: Inactivo
A63: DESREG-062 | B63: PLN | C63: Ley | D63: 26708 | E63: CENTRO INTERNACIONAL PARA LA PROMOCION DE LOS DERECHOS HUMANOS | F63: Modificación | G63: Pendiente
A64: DESREG-063 | B64: PLN | C64: Ley | D64: 25119 | E64: CINEMATECA Y ARCHIVO DE LA IMAGEN NACIONAL, CINEMATECA | F64: Modificación | G64: Pendiente
A65: DESREG-064 | B65: PEN | C65: Decreto | D65: 766/1994 | E65: COMISION NACIONAL DE COMERCIO EXTERIOR | F65: Modificación | G65: Pendiente
A66: DESREG-065 | B66: PLN | C66: Ley | D66: 26117 | E66: COMISION NACIONAL DE MICROCREDITO, MICROCREDITO, ECONOMIA SOCIAL | F66: Modificación | G66: Inactivo
A67: DESREG-066 | B67: PEN | C67: Decreto | D67: 344/2023 | E67: EVALUACION DE TECNOLOGIAS SANITARIAS, CONETEC, EXCELENCIA CLINICA | F67: Modificación | G67: Pendiente
A68: DESREG-067 | B68: PLN | C68: Ley | D68: 419 | E68: COMISION PROTECTORA DE BIBLIOTECAS POPULARES, BIBLIOTECAS POPULARES | F68: Modificación | G68: Inactivo
A69: DESREG-068 | B69: PEN | C69: Decreto | D69: 357/2002 | E69: CONSEJO NACIONAL DE COORDINACION DE POLITICAS SOCIALES, POLITICAS SOCIALES | F69: Modificación | G69: Pendiente
A70: DESREG-069 | B70: PEN | C70: Decreto | D70: 556/2021 | E70: ENTE NACIONAL DE CONTROL Y GESTION DE LA VIA NAVEGABLE, VIA NAVEGABLE | F70: Modificación | G70: Inactivo
A71: DESREG-070 | B71: PLN | C71: Ley | D71: 24583 | E71: ENTE NACIONAL DE OBRAS HIDRICAS DE SANEAMIENTO, OBRAS HIDRICAS, ENOHSA | F71: Modificación | G71: Pendiente
A72: DESREG-071 | B72: PEN | C72: Decreto | D72: 1224/1958 | E72: FONDO NACIONAL DE LAS ARTES | F72: Modificación | G72: Pendiente
A73: DESREG-072 | B73: PEN | C73: Decreto | D73: 1004/2014 | E73: INSTITUTO ARGENTINO DEL TRANSPORTE | F73: Modificación | G73: Inactivo
A74: DESREG-073 | B74: PLN | C74: Ley | D74: 24515 | E74: INSTITUTO NACIONAL CONTRA LA DISCRIMINACION, XENOFOBIA, INADI | F74: Modificación | G74: Inactivo
A75: DESREG-074 | B75: PEN | C75: Decreto | D75: 721/2000 | E75: INSTITUTO NACIONAL DE ASOCIATIVISMO Y ECONOMIA SOCIAL, INAES | F75: Modificación | G75: Pendiente
A76: DESREG-075 | B76: PEN | C76: Decreto | D76: 606/1995 | E76: INSTITUTO NACIONAL DE EDUCACION TECNOLOGICA, INET | F76: Modificación | G76: Pendiente
A77: DESREG-076 | B77: PLN | C77: Ley | D77: 26206 | E77: INSTITUTO NACIONAL DE FORMACION DOCENTE, FORMACION DOCENTE | F77: Modificación | G77: Pendiente
A78: DESREG-077 | B78: PEN | C78: Decreto | D78: 1113/1998 | E78: INSTITUTO NACIONAL DE INVESTIGACIONES HISTORICAS EVA PERON | F78: Modificación | G78: Inactivo
A79: DESREG-078 | B79: PLN | C79: Ley | D79: 25529 | E79: INSTITUTO NACIONAL DE INVESTIGACIONES HISTORICAS JUAN MANUEL DE ROSAS | F79: Modificación | G79: Inactivo
A80: DESREG-079 | B80: PEN | C80: Decreto | D80: 729/2022 | E80: INSTITUTO NACIONAL DE LA AGRICULTURA FAMILIAR CAMPESINA E INDIGENA | F80: Modificación | G80: Inactivo
A81: DESREG-080 | B81: PEN | C81: Decreto | D81: 1286/2010 | E81: INSTITUTO NACIONAL DEL CANCER | F81: Modificación | G81: Inactivo
A82: DESREG-081 | B82: PLN | C82: Ley | D82: 24800 | E82: INSTITUTO NACIONAL DEL TEATRO | F82: Modificación | G82: Pendiente
A83: DESREG-082 | B83: PEN | C83: Decreto | D83: 622/1995 | E83: INSTITUTO NACIONAL JUAN D PERON, ESTUDIOS E INVESTIGACIONES HISTORICAS | F83: Modificación | G83: Inactivo
A84: DESREG-083 | B84: PLN | C84: Ley | D84: 27514 | E84: JUNTA DE SEGURIDAD EN EL TRANSPORTE | F84: Modificación | G84: Inactivo
A85: DESREG-084 | B85: PEN | C85: Decreto | D85: 1133/2015 | E85: MUSEO DE SITIO ESMA, CENTRO CLANDESTINO DE DETENCION | F85: Modificación | G85: Inactivo
A86: DESREG-085 | B86: PEN | C86: Decreto | D86: 357/1997 | E86: ORGANISMO REGULADOR DEL SISTEMA NACIONAL DE AEROPUERTOS, ORSNA | F86: Modificación | G86: Pendiente
A87: DESREG-086 | B87: PEN | C87: Decreto | D87: 348/2017 | E87: PARQUE TECNOPOLIS DEL BICENTENARIO, TECNOPOLIS | F87: Modificación | G87: Inactivo
A88: DESREG-087 | B88: PEN | C88: Decreto | D88: 33405/1944 | E88: TRIBUNAL DE TASACIONES DE LA NACION | F88: Modificación | G88: Pendiente
A89: DESREG-088 | B89: PEN | C89: Decreto | D89: 1244/2013 | E89: UNIDAD EJECUTORA SOTERRAMIENTO, CORREDOR FERROVIARIO CABALLITO MORENO, LINEA SARMIENTO | F89: Modificación | G89: Pendiente
A90: DESREG-089 | B90: PEN | C90: Decreto | D90: 416/2017 | E90: VENTANILLA UNICA DE COMERCIO EXTERIOR, COMERCIO EXTERIOR ARGENTINO | F90: Modificación | G90: Pendiente
A91: DESREG-090 | B91: PLN | C91: Ley | D91: 27015 | E91: UNIVERSIDAD DE LA DEFENSA NACIONAL, UNDEF | F91: Modificación | G91: Pendiente
A92: DESREG-091 | B92: PLN | C92: Ley | D92: 24065 | E92: ENTE NACIONAL REGULADOR DE LA ELECTRICIDAD, ENRE | F92: Modificación | G92: Inactivo
A93: DESREG-092 | B93: PLN | C93: Ley | D93: 24076 | E93: ENTE NACIONAL REGULADOR DEL GAS, ENARGAS | F93: Modificación | G93: Inactivo
A94: DESREG-093 | B94: PEN | C94: Decreto | D94: 1435/1992 | E94: INSTITUTO NACIONAL BELGRANIANO, BELGRANIANO | F94: Modificación | G94: Inactivo
A95: DESREG-094 | B95: PEN | C95: Decreto | D95: 1486/1996 | E95: INSTITUTO NACIONAL BROWNIANO, BROWNIANO | F95: Modificación | G95: Inactivo
A96: DESREG-095 | B96: PLN | C96: Ley | D96: 26534 | E96: INSTITUTO NACIONAL DE MEDICINA TROPICAL, MEDICINA TROPICAL | F96: Modificación | G96: Inactivo
A97: DESREG-096 | B97: PLN | C97: Ley | D97: 19616 | E97: INSTITUTO NACIONAL DE PREVENCION SISMICA, PREVENCION SISMICA, INPRES | F97: Modificación | G97: Inactivo
A98: DESREG-097 | B98: PEN | C98: Decreto | D98: 468/1997 | E98: INSTITUTO NACIONAL NEWBERIANO, NEWBERIANO | F98: Modificación | G98: Inactivo
A99: DESREG-098 | B99: PEN | C99: Decreto | D99: 1368/1958 | E99: INSTITUTO NACIONAL SANMARTINIANO, SANMARTINIANO | F99: Modificación | G99: Pendiente
A100: DESREG-099 | B100: PLN | C100: Ley | D100: 26040 | E100: INSTITUTO NACIONAL YRIGOYENEANO, YRIGOYENEANO | F100: Modificación | G100: Inactivo
...

Sheet Explicaciones
A1: Seguimiento de Propuesta de Desregulación - Libertad y Progreso | D1: Inactivo | E1: =COUNTIF($E$5:$E$1200,D1)
A2: Plazo Junio 2024 - Mayo 2026. | D2: Pendiente | E2: =COUNTIF($E$5:$E$1200,D2) | F2: =SUM(E1:E2)
A4: Nº | B4: Propuesta | C4: Normativa | D4: Resumen | E4: Resultado
A5: DESREG-001 | C5: Resolución 322/2023 - Actualización CUD | D5: Impone plazos fijos para la actualización del Certificado Único de Discapacidad, lo cual es inadecuado para discapacidades permanentes. | E5: =IF(A5=Radar!A2,Radar!G2,0)
A6: DESREG-002 | C6: Decreto 1187/2012 | D6: El mencionado decreto impone la obligación a todo el personal de las jurisdicciones y entidades de la Administración Pública Nacional de recibir sus sueldos mediante la apertura de Cajas de Ahorro Común en el Banco de la Nación Argentina, entidad autárquica del Estado Nacional. | E6: =IF(A6=Radar!A3,Radar!G3,0)
A7: DESREG-003 | C7: Decreto 1191/2012 | D7: Establece que todas las jurisdicciones y entidades del Sector Público Nacional deben optar por las estatales Aerolíneas Argentinas y Austral para la compra de pasajes aéreos, tanto nacionales como internacionales | E7: =IF(A7=Radar!A4,Radar!G4,0)
A8: DESREG-004 | C8: Decreto 557/2023 | D8: En su anexo V establece incrementos a aranceles por encima del AEC del Mercosur. | E8: =IF(A8=Radar!A5,Radar!G5,0)
A9: DESREG-005 | C9: Decreto 557/2023 | D9: Ampliar la baja de aranceles de importación para Bienes de Informática y Telecomunicaciones al 0%. | E9: =IF(A9=Radar!A6,Radar!G6,0)
A10: DESREG-006 | C10: Disposición 21/2023 - Ship to Ship | D10: Exige contratar un proveedor de servicios para operaciones de trasbordo de buque a buque, encareciendo la operación. | E10: =IF(A10=Radar!A7,Radar!G7,0)
A11: DESREG-007 | C11: Decreto 256/2010 - Tráfico hacia Islas Malvinas | D11: Requiere autorización para tránsito entre puertos continentales y las Islas Malvinas, lo cual limita el libre tránsito. | E11: =IF(A11=Radar!A8,Radar!G8,0)
A12: DESREG-008 | C12: Ley 27.419 - Marina Mercante | D12: Sería conveniente eliminar los límites de antigüedad máxima para los buques y reemplazarlos por estándares estrictos de seguridad, mantenimiento y controles medioambientales. Esta es la solución que adoptan la mayoría de los países, incluyendo la Unión Europa y los EEUU y permiten que un barco más antiguo pueda seguir operando si se cumplen los estándares de seguridad y medioambientales. | E12: =IF(A12=Radar!A9,Radar!G9,0)
A13: DESREG-009 | C13: Decreto Ley 19.492 | D13: De 1944 que establece condicionantes y requisitos de tripulación mínima (Art.11º) que encarecen la operatoria y dan un poder desproporcionado a los gremios. | E13: =IF(A13=Radar!A10,Radar!G10,0)
A14: DESREG-010 | C14: Ley 27.418 | D14: Establece que sólo los talleres o proveedores habilitados por Prefectura (PNA) pueden trabajar en los buques (reparar un motor en el muelle es el doble de costoso que hacerlo en una fábrica del GBA). | E14: =IF(A14=Radar!A11,Radar!G11,0)
A15: DESREG-011 | C15: Decreto 2694/1991 | D15: Convendría actualizar y flexibilizar los requisitos de horarios y duración máxima de los servicios de prácticas para bajar los costos de pilotaje, que hoy son extremadamente elevados (un práctico cobra aprox. 20/25.000 US$ por maniobra de Ship to Ship – duración de no más de 3 días). | E15: =IF(A15=Radar!A12,Radar!G12,0)
A16: DESREG-012 | C16: Ley 14.250 de Convenios de Trabajo | D16: Elimina ultraactividad. | E16: =IF(A16=Radar!A13,Radar!G13,0) | F16: Parcialmente modificadas en Ley de Modernización Laboral
A17: DESREG-013 | C17: Ley 14.250 de Convenios de Trabajo | D17: Descentralización de las convenciones colectivas priorizando los convenios de menor nivel (por ejemplo, a nivel empresa) por sobre los de mayor nivel (por sector o actividad). | E17: =IF(A17=Radar!A14,Radar!G14,0)
A18: DESREG-014 | C18: Ley 14.250 de Convenios de Trabajo | D18: Introducción de un mecanismo de arbitraje oficial que facilite e incentive la resolución de conflictos laborales entre las partes. | E18: =IF(A18=Radar!A15,Radar!G15,0)
A19: DESREG-015 | C19: Ley 12.988/1947 - Seguros en el Exterior | D19: Prohíbe a los argentinos contratar seguros fuera del país, creando un monopolio para aseguradoras locales. | E19: =IF(A19=Radar!A16,Radar!G16,0)
A20: DESREG-016 | C20: Decreto 2426/2012 - Asignación de Frecuencias | D20: Permite asignación de frecuencias directamente a entidades estatales, limitando la competencia privada. | E20: =IF(A20=Radar!A17,Radar!G17,0)
A21: DESREG-017 | C21: Decreto 915/2010 | D21: Crea el Programa Nacional para el Desarrollo de Parques Industriales | E21: =IF(A21=Radar!A18,Radar!G18,0)
A22: DESREG-018 | C22: Decreto 68/2022 | D22: Contempla el otorgamiento de Aportes No Reintegrables para estudios, obras, ampliaciones y proyectos productivos en parques industriales inscriptos en el REGISTRO NACIONAL DE PARQUES INDUSTRIALES (RENPI) creado por el Decreto 915/2010. | E22: =IF(A22=Radar!A19,Radar!G19,0)
A23: DESREG-019 | C23: Resolución 155/2007 - Subsidio a Minoristas | D23: Compensa a minoristas que comercialicen papa de ciertas características, encareciendo la intervención estatal. | E23: =IF(A23=Radar!A20,Radar!G20,0)
A24: DESREG-020 | C24: Resolución 684/2014 - Subsidio a Productores Lecheros | D24: Otorga subsidios a productores tamberos según la producción incremental, incrementando el gasto fiscal discrecional. | E24: =IF(A24=Radar!A21,Radar!G21,0)
A25: DESREG-021 | C25: Resolución 208/2014 | D25: Crea el registro para los beneficiarios de la Resolución 684/2014 | E25: =IF(A25=Radar!A22,Radar!G22,0)
A26: DESREG-022 | C26: Resolución 50/2015 - Patrocinio Jurídico Gratuito | D26: Establece patrocinio gratuito en conflictos de consumo, generando un gasto adicional sin evaluar la situación fiscal. | E26: =IF(A26=Radar!A23,Radar!G23,0)
A27: DESREG-023 | C27: Resolución 1/2006 - Precios Máximos de Carne | D27: Fija precios en toda la cadena de la carne, afectando el libre mercado y distorsionando la oferta. Si bien se ha dejado de aplicar, es conveniente derogarla. | E27: =IF(A27=Radar!A24,Radar!G24,0)
A28: DESREG-024 | C28: Resolución Conjunta 1/2016 - Programa “El Mercado en tu Barrio” | D28: Promueve ferias de productos agroalimentarios, asumiendo funciones que no corresponden al Estado. | E28: =IF(A28=Radar!A25,Radar!G25,0)
A29: DESREG-025 | C29: Resolución 3597/2016 - Programa Conectividad | D29: Subsidia proyectos de conectividad en áreas rurales, aumentando el gasto público en telecomunicaciones. | E29: =IF(A29=Radar!A26,Radar!G26,0) | F29: https://servicios.infoleg.gob.ar/infolegInternet/anexos/420000-424999/421850/norma.htm
A30: DESREG-026 | C30: Resolución 63/2011 - Secretaría de Comercio | D30: Crea un Programa destinado a promover la formación de una red de Mercados concentradores de Interés Nacional. | E30: =IF(A30=Radar!A27,Radar!G27,0)
A31: DESREG-027 | C31: Resolución 1280/2023 - Secretaría de Agricultura | D31: Crea el “Programa de Aporte de Nutrientes 2023” en el ámbito de la Secretaria de Agricultura, Ganadería y Pesca, destinado a brindar apoyo a pequeños productores de trigo y maíz para el incremento de las dosis medias de fertilización nitrogenada. | E31: =IF(A31=Radar!A28,Radar!G28,0)
A32: DESREG-028 | C32: Resolución 142/2021 - Secretaría de Alimentos, Bioeconomia y Desarrollo Regional | D32: Crea el PROGRAMA AGROPyMES SUSTENTABLES en el ámbito de la Secretaría de Alimentos, Bioeconomía y Desarrollo Regional. | E32: =IF(A32=Radar!A29,Radar!G29,0)
A33: DESREG-029 | C33: Resolución Conjunta 26/2021 - Secretaría de Calidad en Salud y Secretaría de Alimentos, Bioeconomia y Desarrollo Regional | D33: Establece la obligación de incorporar el número de Registro Nacional de Producto Alimenticio en el rótulo de todos los productos alimenticios autorizados en el Código Alimentario Argentino. | E33: =IF(A33=Radar!A30,Radar!G30,0)
A34: DESREG-030 | C34: Resolución 26/2021 - Ministerio de Desarrollo Productivo | D34: Crea el Programa "Agencia de Promoción para la Capacitación de las PyMEs" | E34: =IF(A34=Radar!A31,Radar!G31,0) | F34: En vigencia pero sin funcionamiento
A35: DESREG-031 | C35: Disposición 9/2019 - Dirección Nacional de Control Agropecuario | D35: Establece que en los contratos de compraventa de granos con entrega de mercaderías cuyo precio se halle nominado en dólares estadounidenses. Según esta disposición la cancelación —tanto total como parcial— deberá realizarse tomando en cuenta el tipo de cambio dólar divisa del BNA. | E35: =IF(A35=Radar!A32,Radar!G32,0) | F35: Derogada por Resolución 112/2024
A36: DESREG-032 | C36: Disposición 1675/2014 - ANMAT | D36: En su Art.17º establece que las inscripciones en el Registro Nacional de Establecimientos elaboradores de productos alimenticios o de suplementos dietarios tengan una vigencia máxima de 5 años. Tras lo cual, se debe solicitar su renovación. | E36: =IF(A36=Radar!A33,Radar!G33,0)
A37: DESREG-033 | C37: RG 1025/2024 CNV | D37: Propuso regular a los “Prestadores de Servicios con Activos Virtuales” es decir, las empresas que operan con crypto. La resolución es bastante draconiana y trata a cada uno de estos PSAV como si fuese poco menos que un banco. | E37: =IF(A37=Radar!A34,Radar!G34,0) | F37: La RG 1058/2025 modifica, categoriza y simplifica la burocracia. Sigue existiendo el registro por el GAFI, pero se simplifica y normaliza bastante
A38: DESREG-034 | C38: Ley 26.854 - Ley de Medidas Cautelares contra el Estado Nacional | D38: Estableció numerosas restricciones para la concesión de medidas cautelares contra el Estado nacional que en muchos casos la mayoría de la doctrina juzga, con razón, inconstitucionales. | E38: =IF(A38=Radar!A35,Radar!G35,0)
A39: DESREG-035 | C39: Ley 25.344 - Emergencia Económica | D39: En sus artículos 8, 9 y 10, establece un procedimiento por el cual, cuando se inicia una demanda contra el Estado nacional (sus entes descentralizados o incluso empresas con participación estatal), debe adelantarse una copia de la demanda (y de toda la documentación y prueba acompañada) aún antes de que el juez disponga su traslado. Además de ser un trámite innecesario que carga a los particulares con costo y pérdida de tiempo, pone al Estado nacional en una situación de privilegio y ventaja | E39: =IF(A39=Radar!A36,Radar!G36,0)
A40: DESREG-036 | C40: Ley 25.345 - | D40: Priva de efectos entre partes y frente a terceros a los pagos totales o parciales de sumas de dinero en efectivo superiores a 1.000 pesos. | E40: =IF(A40=Radar!A37,Radar!G37,0)
A41: DESREG-037 | C41: Ley 19.549 - Ley de Procedimiento Administrativo | D41: Proponemos una norma similar a la que existe en Chile (reforma Piñeira). El estado no puede pedir un documento que emite el mismo estado (por ejemplo, DNIs, o certificados de no haber cometido crímenes, o certificados de AFIP). | E41: =IF(A41=Radar!A38,Radar!G38,0)
A42: DESREG-038 | C42: Varios regímenes de información AFIP | D42: Existen muchísimos regímenes de información de AFIP: expensas, colegios, bancos, registros de la propiedad, escribanos, fideicomisos, contadores, PSP, Alycs, etc. etc. Esto es privatizar el trabajo de AFIP y juntar información que en la gran mayoría de los casos duplica y triplica el trabajo y la información. Esto no tiene sentido, genera costos en el sector privado y no tiene sentido. Proponemos en principio eliminar todos. | E42: =IF(A42=Radar!A39,Radar!G39,0) | F42: avances menores en ... https://www.argentina.gob.ar/noticias/eliminacion-del-regimen-de-informacion-para-operaciones-economicas-entre-residentes-y | G42: Ley de inocencia fiscal
A43: DESREG-039 | C43: Ley 19.550 - De Sociedades Comerciales | D43: Continúa siendo un obstáculo para invertir en la Argentina enfrentarse a la disparidad de criterios de los distintos regímenes locales y a la burocracia y demora de los mismos. Deberíamos ir a la igualdad total hacer como otros países (Estados Unidos, Paraguay, Chile, Uruguay) y que el principio es que las sociedades extranjeras pueden participar en una sociedad local sin ningún tipo de inscripción o registro previo. | E43: =IF(A43=Radar!A40,Radar!G40,0)
A44: DESREG-040 | C44: RG 9/2015 - IGJ | D44: Desde el año 2015 se le exige a los directores una garantía que en los hechos se cubre con un seguro de caución. Esa garantía siempre es realmente insignificante y lo único que hizo fue crear un mercado cautivo a compañías de seguros. | E44: =IF(A44=Radar!A41,Radar!G41,0)
A45: DESREG-041 | C45: Disposición ANMAT 3226/2011 | D45: Prohibe la importación, distribución, comercialización y publicidad del cigarrillo electrónico que contenga nicotina, sus accesorios y cartuchos | E45: =IF(A45=Radar!A42,Radar!G42,0) | F45: es de jon
A46: DESREG-042 | C46: Res. MS 565/2023 | D46: Prohibe la importación, distribución, comercialización y la publicidad de todos los sistemas o dispositivos electrónicos destinados a inhalar vapores o aerosoles de tabaco, denominados habitualmente como “Productos de Tabaco Calentado”. | E46: =IF(A46=Radar!A43,Radar!G43,0) | F46: Es de Jon.
A47: DESREG-043 | C47: Resolución SENASA 1678/2019 | D47: El SENASA obliga a que los viveros se anoten en el Registro Nacional Fitosanitario de Operadores de Material de Propagación, Micropropagación y/o Multiplicación Vegetal (RENFO) | E47: =IF(A47=Radar!A44,Radar!G44,0) | F47: Abrogada por Res64/2026
A48: DESREG-044 | C48: Resolución SENASA N°1039/2018 | D48: Crea la figura del “Responsable Técnico", que se encuentra autorizado a realizar las auditorías del registro, y también crea el “Registro Nacional Único de Responsables Técnicos”. | E48: =IF(A48=Radar!A45,Radar!G45,0)
A49: DESREG-045 | C49: Comunicación "A" 7535 del BCRA | D49: Eliminación de la prohibición de financiación en cuotas para compras internacionales que se reciben por el sistema de envíos postales sin finalidad comercial | E49: =IF(A49=Radar!A46,Radar!G46,0) | F49: A priori pareceria seguir vigente. Revisar
A50: DESREG-046 | C50: Resolución General 5608/2024 | D50: Supresión del requisito de la dirección fiscal electrónica en las compras bajo el régimen de pequeños envíos con el fin de simplificar los trámites aduaneros y facilitar el acceso a este esquema para todos los consumidores. | E50: =IF(A50=Radar!A47,Radar!G47,0)
A51: DESREG-047 | C51: Decreto 406/2019 | D51: Modernización del CIBU y facilitación de la importación de bienes usados. | E51: =IF(A51=Radar!A48,Radar!G48,0)
A52: DESREG-048 | C52: Resolución General 4447/2019 | D52: Mejoras a las condiciones del régimen puerta a puerta y reducción de la burocracia asociada. | E52: =IF(A52=Radar!A49,Radar!G49,0)
A53: DESREG-049 | C53: Ley 25.467 | D53: Es imperativo revisar el actual sistema de promoción y financiamiento de la ciencia en Argentina. La Ley 25.467, promulgada en 2001, estableció un marco de planificación estatal que ha demostrado ser ineficiente, burocrático y costoso. Esta normativa no solo impone un modelo rígido de gestión científica, sino que también desalienta la inversión privada, perpetuando la dependencia del sector científico en los fondos públicos. | E53: =IF(A53=Radar!A50,Radar!G50,0)
A54: DESREG-050 | C54: Ley 19.459 | D54: Modificar la Ley de Procedimientos Adminsitrativos para establecer el silencio administrativo en sentido positivo dentro de una serie de normas que exijan una autorización administrativa para que los particulares puedan llevar a cabo una determinada conducta o acto. | E54: =IF(A54=Radar!A51,Radar!G51,0)
A55: DESREG-051 | C55: Ley 19.550 | D55: Simplificación de la inscripción de sociedades extranjeras ante la IGJ, adoptando el modelo de EE.UU., Paraguay, Chile y Uruguay. | E55: =IF(A55=Radar!A52,Radar!G52,0) | F55: avances menores en ... | G55: duplicado en desreg039
A56: DESREG-052 | C56: Resolución General IGJ 15/2024 | D56: Esta propuesta busca equilibrar la necesidad de fiscalización con la simplificación de trámites, eliminando requisitos redundantes y facilitando la operación de las fundaciones para que puedan enfocarse en sus objetivos sociales. | E56: =IF(A56=Radar!A53,Radar!G53,0)
A57: DESREG-053 | C57: Ley 27.275 | D57: AGENCIA DE ACCESO A LA INFORMACIÓN PÚBLICA | E57: =IF(A57=Radar!A54,Radar!G54,0)
A58: DESREG-054 | C58: Decreto 157/2020 | D58: AGENCIA NACIONAL DE PROMOCIÓN DE LA INVESTIGACIÓN, EL DESARROLLO TECNOLÓGICO Y LA INNOVACIÓN | E58: =IF(A58=Radar!A55,Radar!G55,0)
A59: DESREG-055 | C59: Ley 26.363 | D59: AGENCIA NACIONAL DE SEGURIDAD VIAL | E59: =IF(A59=Radar!A56,Radar!G56,0)
A60: DESREG-056 | C60: Ley 27.669 | D60: AGENCIA REGULATORIA DE LA INDUSTRIA DEL CÁÑAMO Y DEL CANNABIS MEDICINAL (ARICCAME) | E60: =IF(A60=Radar!A57,Radar!G57,0)
A61: DESREG-057 | C61: Decreto 1259/2003 | D61: ARCHIVO NACIONAL DE LA MEMORIA | E61: =IF(A61=Radar!A58,Radar!G58,0)
A62: DESREG-058 | C62: Ley 23.329 | D62: BALLET NACIONAL | E62: =IF(A62=Radar!A59,Radar!G59,0)
A63: DESREG-059 | C63: Ley 26.548 | D63: BANCO NACIONAL DE DATOS GENÉTICOS | E63: =IF(A63=Radar!A60,Radar!G60,0)
A64: DESREG-060 | C64: Decreto 195/2011 | D64: CASA PATRIA GRANDE 'PRESIDENTE NÉSTOR CARLOS KIRCHNER' | E64: =IF(A64=Radar!A61,Radar!G61,0)
A65: DESREG-061 | C65: Decreto 348/2017 | D65: CENTRO CULTURAL DEL BICENTENARIO 'PRESIDENTE DR. NÉSTOR CARLOS KIRCHNER' | E65: =IF(A65=Radar!A62,Radar!G62,0)
A66: DESREG-062 | C66: Ley 26.708 | D66: CENTRO INTERNACIONAL PARA LA PROMOCIÓN DE LOS DERECHOS HUMANOS | E66: =IF(A66=Radar!A63,Radar!G63,0)
A67: DESREG-063 | C67: Ley 25.119 | D67: CINEMATECA Y ARCHIVO DE LA IMAGEN NACIONAL | E67: =IF(A67=Radar!A64,Radar!G64,0)
... A74: DESREG-070 | C74: Ley 24.583 | D74: ENTE NACIONAL DE OBRAS HÍDRICAS DE SANEAMIENTO | E74: =IF(A74=Radar!A71,Radar!G71,0)
A75: DESREG-071 | C75: Decreto 1224/1958 | D75: FONDO NACIONAL DE LAS ARTES | E75: =IF(A75=Radar!A72,Radar!G72,0) | F75: A priori sigue vigente pero fue muy modificado por el Decreto 1029/2024 - Decreto 772/2025 modifica estructura
A76: DESREG-072 | C76: Decreto 1004/2014 | D76: INSTITUTO ARGENTINO DEL TRANSPORTE | E76: =IF(A76=Radar!A73,Radar!G73,0)
A77: DESREG-073 | C77: Ley 24.515 | D77: INSTITUTO NACIONAL CONTRA LA DISCRIMINACIÓN, LA XENOFOBIA Y EL RACISMO | E77: =IF(A77=Radar!A74,Radar!G74,0)
A78: DESREG-074 | C78: Decreto 721/2000 | D78: INSTITUTO NACIONAL DE ASOCIATIVISMO Y ECONOMÍA SOCIAL | E78: =IF(A78=Radar!A75,Radar!G75,0)
A79: DESREG-075 | C79: Decreto 606/1995 | D79: INSTITUTO NACIONAL DE EDUCACIÓN TECNOLÓGICA | E79: =IF(A79=Radar!A76,Radar!G76,0)
A80: DESREG-076 | C80: Ley 26.206 | D80: INSTITUTO NACIONAL DE FORMACIÓN DOCENTE | E80: =IF(A80=Radar!A77,Radar!G77,0)
A81: DESREG-077 | C81: Decreto 1113/1998 | D81: INSTITUTO NACIONAL DE INVESTIGACIONES HISTÓRICAS EVA PERÓN | E81: =IF(A81=Radar!A78,Radar!G78,0)
A82: DESREG-078 | C82: Ley 25.529 | D82: INSTITUTO NACIONAL DE INVESTIGACIONES HISTÓRICAS JUAN MANUEL DE ROSAS | E82: =IF(A82=Radar!A79,Radar!G79,0)
A83: DESREG-079 | C83: Decreto 729/2022 | D83: INSTITUTO NACIONAL DE LA AGRICULTURA FAMILIAR, CAMPESINA E INDÍGENA | E83: =IF(A83=Radar!A80,Radar!G80,0)
A84: DESREG-080 | C84: Decreto 1286/2010 | D84: INSTITUTO NACIONAL DEL CÁNCER | E84: =IF(A84=Radar!A81,Radar!G81,0)
A85: DESREG-081 | C85: Ley 24.800 | D85: INSTITUTO NACIONAL DEL TEATRO | E85: =IF(A85=Radar!A82,Radar!G82,0)
A86: DESREG-082 | C86: Decreto 622/1995 | D86: INSTITUTO NACIONAL 'JUAN D. PERÓN' DE ESTUDIOS E INVESTIGACIONES HISTÓRICAS, SOCIALES Y POLÍTICAS | E86: =IF(A86=Radar!A83,Radar!G83,0)
A87: DESREG-083 | C87: Ley 27.514 | D87: JUNTA DE SEGURIDAD EN EL TRANSPORTE | E87: =IF(A87=Radar!A84,Radar!G84,0)
... A91: DESREG-087 | C91: Decreto 33405/1944 | D91: TRIBUNAL DE TASACIONES DE LA NACIÓN | E91: =IF(A91=Radar!A88,Radar!G88,0)
A92: DESREG-088 | C92: Decreto 1244/2013 | D92: UNIDAD EJECUTORA DE LA OBRA DE SOTERRAMIENTO DEL CORREDOR FERROVIARIO CABALLITO-MORENO DE LA LÍNEA SARMIENTO | E92: =IF(A92=Radar!A89,Radar!G89,0) | F92: se paralizo la obra
A93: DESREG-089 | C93: Decreto 416/2017 | D93: UNIDAD EJECUTORA DEL RÉGIMEN NACIONAL DE VENTANILLA ÚNICA DE COMERCIO EXTERIOR ARGENTINO | E93: =IF(A93=Radar!A90,Radar!G90,0)
A94: DESREG-090 | C94: Ley 27.015 | D94: UNIVERSIDAD DE LA DEFENSA NACIONAL | E94: =IF(A94=Radar!A91,Radar!G91,0)
A95: DESREG-091 | C95: Ley 24.065 | D95: ENTE NACIONAL REGULADOR DE LA ELECTRICIDAD | E95: =IF(A95=Radar!A92,Radar!G92,0)
A96: DESREG-092 | C96: Ley 24.076 | D96: ENTE NACIONAL REGULADOR DEL GAS | E96: =IF(A96=Radar!A93,Radar!G93,0)
A97: DESREG-093 | C97: Decreto 1435/1992 | D97: INSTITUTO NACIONAL BELGRANIANO | E97: =IF(A97=Radar!A94,Radar!G94,0)
A98: DESREG-094 | C98: Decreto 1486/1996 | D98: INSTITUTO NACIONAL BROWNIANO | E98: =IF(A98=Radar!A95,Radar!G95,0)
A99: DESREG-095 | C99: Ley 26.534 | D99: INSTITUTO NACIONAL DE MEDICINA TROPICAL | E99: =IF(A99=Radar!A96,Radar!G96,0)
A100: DESREG-096 | C100: Ley 19.616 | D100: INSTITUTO NACIONAL DE PREVENCIÓN SÍSMICA | E100: =IF(A100=Radar!A97,Radar!G97,0)
A101: DESREG-097 | C101: Decreto 468/1997 | D101: INSTITUTO NACIONAL NEWBERIANO | E101: =IF(A101=Radar!A98,Radar!G98,0)
A102: DESREG-098 | C102: Decreto 1368/1958 | D102: INSTITUTO NACIONAL SANMARTINIANO | E102: =IF(A102=Radar!A99,Radar!G99,0)
A103: DESREG-099 | C103: Ley 26.040 | D103: INSTITUTO NACIONAL YRIGOYENEANO | E103: =IF(A103=Radar!A100,Radar!G100,0)
A104: DESREG-100 | C104: Decreto 318/1996 | D104: TEATRO NACIONAL CERVANTES | E104: =IF(A104=Radar!A101,Radar!G101,0)
A105: DESREG-101 | D105: HOSPITAL NACIONAL EN RED ESPECIALIZADO EN SALUD MENTAL Y ADICCIONES 'LIC. LAURA BONAPARTE' | E105: =IF(A105=Radar!A102,Radar!G102,0)
A106: DESREG-102 | D106: HOSPITAL NACIONAL 'BALDOMERO SOMMER' | E106: =IF(A106=Radar!A103,Radar!G103,0)
A107: DESREG-103 | D107: HOSPITAL NACIONAL 'PROFESOR ALEJANDRO POSADAS' | E107: =IF(A107=Radar!A104,Radar!G104,0)
A108: DESREG-104 | D108: HOSPITAL NACIONAL Y COMUNIDAD DR. RAMÓN CARRILLO | E108: =IF(A108=Radar!A105,Radar!G105,0)
A109: DESREG-105 | C109: Ley 19.337 | D109: INSTITUTO NACIONAL DE REHABILITACIÓN PSICOFÍSICA DEL SUR 'DR. JUAN OTIMIO TESONE' | E109: =IF(A109=Radar!A106,Radar!G106,0)
A110: DESREG-106 | C110: Decreto 1286/2010 | D110: INSTITUTO NACIONAL DEL CANCER | E110: =IF(A110=Radar!A107,Radar!G107,0)
...
